keras_pyramid_pooling_module/__init__.py
keras_pyramid_pooling_module/pyramid_pooling_module.py
keras_pyramid_pooling_module-1.1.8.dist-info/LICENSE
keras_pyramid_pooling_module-1.1.8.dist-info/METADATA
keras_pyramid_pooling_module-1.1.8.dist-info/WHEEL
keras_pyramid_pooling_module-1.1.8.dist-info/top_level.txt
keras_pyramid_pooling_module-1.1.8.dist-info/RECORD
