Metadata-Version: 2.1
Name: keras-pyramid-pooling-module
Version: 1.1.8
Summary: The Pyramid Pooling Module for Keras.
Home-page: https://github.com/Kautenja/keras-pyramid-pooling-module
Author: Christian Kauten
Author-email: kautencreations@gmail.com
License: MIT
Keywords: Keras Pyramid-Pooling-Module Layer
Platform: UNKNOWN
Classifier: License :: Free For Educational Use
Classifier: Development Status :: 5 - Production/Stable
Classifier: Intended Audience :: Developers
Classifier: Intended Audience :: Science/Research
Classifier: Operating System :: MacOS :: MacOS X
Classifier: Operating System :: POSIX :: Linux
Classifier: Programming Language :: Python :: 3.5
Classifier: Programming Language :: Python :: 3.6
Classifier: Programming Language :: Python :: 3.7
Classifier: Programming Language :: Python :: 3.8
Classifier: Topic :: Scientific/Engineering :: Artificial Intelligence
Classifier: Topic :: Software Development :: Libraries :: Python Modules
Requires-Dist: Keras (>=2.4.3)
Requires-Dist: tensorflow (>=2.4.1)
